README.rst
setup.cfg
setup.py
./__init__.py
./product.py
./product.xml
./sale.py
./sale.xml
./stock.py
./stock.xml
./tryton.cfg
./locale/de_DE.po
./tests/__init__.py
./tests/test_sale.py
./tests/test_views_depends.py
./view/move_form.xml
./view/move_tree.xml
./view/sale_line_form.xml
./view/sale_line_tree.xml
fio_sale_available_stock.egg-info/PKG-INFO
fio_sale_available_stock.egg-info/SOURCES.txt
fio_sale_available_stock.egg-info/dependency_links.txt
fio_sale_available_stock.egg-info/entry_points.txt
fio_sale_available_stock.egg-info/not-zip-safe
fio_sale_available_stock.egg-info/requires.txt
fio_sale_available_stock.egg-info/top_level.txt